pylyra.so
pylyra-1.0.dist-info/DESCRIPTION.rst
pylyra-1.0.dist-info/METADATA
pylyra-1.0.dist-info/RECORD
pylyra-1.0.dist-info/WHEEL
pylyra-1.0.dist-info/metadata.json
pylyra-1.0.dist-info/top_level.txt
