Metadata-Version: 2.0
Name: pylyra
Version: 1.0
Summary: Python implementation of Lyra2
Home-page: https://github.com/leocalm/pylyra
Author: Leonardo C. Almeida
Author-email: leocalm@gmail.com
License: MIT
Keywords: security password development
Platform: UNKNOWN
Classifier: Development Status :: 4 - Beta
Classifier: Intended Audience :: Developers
Classifier: Topic :: Security :: Cryptography
Classifier: License :: OSI Approved :: MIT License
Classifier: Programming Language :: Python :: 2
Classifier: Programming Language :: Python :: 2.7
Classifier: Programming Language :: Python :: 3
Classifier: Programming Language :: Python :: 3.3
Classifier: Programming Language :: Python :: 3.4
Classifier: Programming Language :: Python :: 3.5
Classifier: Programming Language :: Python :: 3.6
